cybralist/__init__.py
cybralist-1.0.0.dist-info/LICENSE
cybralist-1.0.0.dist-info/METADATA
cybralist-1.0.0.dist-info/WHEEL
cybralist-1.0.0.dist-info/top_level.txt
cybralist-1.0.0.dist-info/RECORD
