Metadata-Version: 2.1
Name: cybralist
Version: 1.0.0
Summary: API for cybralist.com
Home-page: UNKNOWN
Author: Cybrancee
License: UNKNOWN
Platform: UNKNOWN
Classifier: Programming Language :: Python :: 3
Classifier: License :: OSI Approved :: MIT License
Classifier: Operating System :: OS Independent
Requires-Python: >=3.6
License-File: LICENSE
Requires-Dist: aiohttp
